{
  "tipoActo": "inicio_actividades",
  "vigenciaActoFecha": "2026-07-01",
  "tipoEntidad": "persona_fisica",
  "nombreDenominacion": "Julio César Méndez Acosta",
  "esResidente": true,
  "domicilioFiscalCalidadOcupante": "propietario",
  "domicilioFiscalDepartamento": "Canelones",
  "domicilioFiscalLocalidad": "Ciudad de la Costa",
  "domicilioFiscalCalle": "Ruta Interbalnearia",
  "domicilioFiscalNumero": "8765",
  "domicilioFiscalCodigoPostal": "15008",
  "domicilioFiscalTelefonoFijo": "26771234",
  "domicilioConstituidoIgualAlFiscal": true,
  "actividadPrincipalDescripcion": "Servicios de contabilidad y asesoramiento tributario",
  "actividadPrincipalGrupo": "69",
  "obligacionIva": true,
  "obligacionIrpf": true,
  "obligacionMonotributo": false,
  "fechaBalance": "12-31",
  "regimenAportacionBps": "servicios_personales",
  "titularTipoDocumento": "CI",
  "titularNumeroDocumento": "3987654",
  "titularPaisOrigenDocumento": "Uruguay",
  "titularPrimerApellido": "Méndez",
  "titularSegundoApellido": "Acosta",
  "titularPrimerNombre": "Julio",
  "titularSegundoNombre": "César",
  "titularFechaNacimiento": "1975-11-02",
  "titularEstadoCivil": "casado",
  "titularSexo": "M",
  "titularTipoResidencia": "residente",
  "titularDomicilioDepartamento": "Canelones",
  "titularDomicilioLocalidad": "Ciudad de la Costa",
  "titularDomicilioCalle": "Ruta Interbalnearia",
  "titularDomicilioNumero": "8765",
  "titularDomicilioCodigoPostal": "15008",
  "titularTelefonoMovil": "098765432",
  "titularCorreoElectronico": "julio.mendez@example.com",
  "segundoTitularPresente": true,
  "segundoTitularVinculo": "representante",
  "segundoTitularTipoDocumento": "CI",
  "segundoTitularNumeroDocumento": "4556677",
  "segundoTitularPaisOrigenDocumento": "Uruguay",
  "segundoTitularPrimerApellido": "Fernández",
  "segundoTitularPrimerNombre": "Ana",
  "observaciones": "Presentación a cargo de contadora pública autorizada."
}
