{
  "surname": "Adeyemi",
  "otherNames": "Chinedu Bola",
  "sex": "male",
  "maritalStatus": "single",
  "presentNationality": "British",
  "dateOfBirth": "1990-04-12",
  "placeOfBirth": "Lagos, Nigeria",
  "residentialAddress": "14 Kingsway Road, Manchester, M14 5RT, United Kingdom",
  "residentialTelephone": "+44 161 555 0134",
  "profession": "Software Engineer",
  "hairColour": "Black",
  "eyeColour": "Brown",
  "height": "178cm",
  "passportNumber": "P0123456789",
  "passportIssueDate": "2022-03-01",
  "passportExpiryDate": "2032-02-28",
  "passportPlaceOfIssue": "Manchester",
  "passportIssuingGovernment": "United Kingdom",
  "purposeOfJourney": "Tourism — visiting family and sightseeing for two weeks",
  "numberOfEntriesRequired": "single",
  "intendedDurationOfStay": "14 days",
  "proposedDateOfTravel": "2026-09-05",
  "modeOfTravelToNigeria": "Air",
  "fundsAvailableForTrip": "USD 2,500",
  "intendedAddressInNigeria": "22 Adeola Odeku Street, Victoria Island, Lagos",
  "previousNigerianVisaApplied": "no",
  "previouslyVisitedNigeria": "no",
  "yearsLivedInApplyingCountry": "12 years",
  "everInfectedContagiousDiseaseOrMentalIllness": "no",
  "everArrestedOrConvicted": "no",
  "everInvolvedNarcoticActivities": "no",
  "everDeported": "no",
  "everSoughtVisaByMisrepresentationOrFraud": "no",
  "everTestedPositiveHivAids": "no",
  "signatureDate": "2026-07-20",
  "documents": [
    { "id": "applicantPhoto", "provided": true },
    { "id": "originalPassport", "provided": true },
    { "id": "letterOfInvitationFromNigeria", "provided": true },
    { "id": "returnPrepaidMailer", "provided": true },
    { "id": "childUnder16Requirements", "provided": false },
    { "id": "onlineVisaFeePayment", "provided": true },
    { "id": "processingFeeMoneyOrder", "provided": true },
    { "id": "expeditedProcessingFeeMoneyOrder", "provided": false },
    { "id": "applicationCertification", "provided": true }
  ]
}
